__init__.py
community_layout/__init__.py
community_layout/layout_class.py
community_layout-1.0.6.dist-info/LICENSE
community_layout-1.0.6.dist-info/METADATA
community_layout-1.0.6.dist-info/WHEEL
community_layout-1.0.6.dist-info/top_level.txt
community_layout-1.0.6.dist-info/RECORD
