Metadata-Version: 2.1
Name: community-layout
Version: 1.0.6
Summary: A Python package for community-separated layout of large networkx graphs.
Author-email: Alex Davies <alexander.davies@bristol.ac.uk>
License: GNU GENERAL PUBLIC LICENSE
Project-URL: Homepage, https://github.com/neutralpronoun/CommunityLayout.git
Keywords: networkx,graph,community,layout
Classifier: Development Status :: 1 - Planning
Classifier: Intended Audience :: Science/Research
Classifier: License :: OSI Approved :: GNU General Public License v3 (GPLv3)
Classifier: Operating System :: POSIX :: Linux
Classifier: Programming Language :: Python :: 3
Requires-Python: >=3.6
License-File: LICENSE
Requires-Dist: networkx
Provides-Extra: dev
Requires-Dist: datashader ; extra == 'dev'
Requires-Dist: scikit-image ; extra == 'dev'
